asyncx/__init__.py
asyncx/exceptions.py
asyncx/sync_to_async.py
asyncx/task_manager.py
asyncx_tools-0.1.0.dist-info/METADATA
asyncx_tools-0.1.0.dist-info/WHEEL
asyncx_tools-0.1.0.dist-info/top_level.txt
asyncx_tools-0.1.0.dist-info/RECORD
