Metadata-Version: 2.4
Name: asyncx-tools
Version: 0.1.0
Summary: 非同期タスク管理・同期/非同期変換ライブラリ
Home-page: https://github.com/tikipiya/asyncx
Author: tikisan
Author-email: s2501082@sendai-nct.jp
Classifier: Programming Language :: Python :: 3
Classifier: License :: OSI Approved :: MIT License
Classifier: Operating System :: OS Independent
Requires-Python: >=3.7
Requires-Dist: typing-extensions>=4.0.0
Dynamic: author
Dynamic: author-email
Dynamic: classifier
Dynamic: description
Dynamic: description-content-type
Dynamic: home-page
Dynamic: requires-dist
Dynamic: requires-python
Dynamic: summary
